Metadata-Version: 2.1
Name: silg
Version: 0.0.1
Summary: Situated Interative Language Grounding Benchmark.
Home-page: https://github.com/vzhong/silg
Author: Victor Zhong
Author-email: victor@victorzhong.com
License: MIT
Keywords: text nlp machine-learning
Platform: UNKNOWN
Classifier: Development Status :: 3 - Alpha
Classifier: Intended Audience :: Developers
Classifier: License :: OSI Approved :: MIT License
Classifier: Programming Language :: Python :: 3
Requires-Python: >=3.7.10
Provides-Extra: dev
Provides-Extra: test
